rtl/alu.v
/*
 *inst[3:0]  =  4'h0 => reserved
 *inst[3:0]  =  4'h1 => Addition  
 *inst[3:0]  =  4'h2 => Substraction

 *inst[3:0]  =  4'h3 => Multiply  
 *inst[3:0]  =  4'h4 => division  
 *inst[3:0]  =  4'h5 => shift right
 *inst[3:0]  =  4'h6 => shift left
 *inst[3:0]  =  4'h7 => logical AND
 *inst[3:0]  =  4'h8 => logical OR
 *inst[3:0]  =  4'h9 => Bitwise AND
 *inst[3:0]  =  4'hA => Bitwise OR
 *inst[3:0]  =  4'hB => XOR        
 *inst[3:0]  =  4'hC => Reserved  
 *inst[3:0]  =  4'hD => Reserved  
 *inst[3:0]  =  4'hE => Reserved  
 *inst[3:0]  =  4'hF => Reserved  
 *
 *
 */


`timescale 1ns/100ps

module alu8bit (
      input [3:0] inst ,
      input [7:0] op_a,
      input [7:0] op_b,
      output [7:0] op_out
   );


reg [8:0] op_out_int;

assign op_out = op_out_int[7:0];

always @(*) begin
 case (inst)
   4'h1 :  //
       op_out_int = op_a + op_b ;  // can instantiate a adder here
   4'h2 :  //
       op_out_int = op_a - op_b ;
   4'h3 :  //
       op_out_int = op_a * op_b ;
   4'h4 :  //
       op_out_int = op_a / op_b ;
   4'h5 :  //
       op_out_int = op_a >> 1  ;
   4'h6 :  //
       op_out_int = op_a << 1 ;
   4'h7 :  //
       op_out_int = op_a && op_b ;
   4'h8 :  //
       op_out_int = op_a || op_b ;
   4'h9 :  //
       op_out_int = op_a & op_b ;
   4'hA :  //
       op_out_int = op_a | op_b ;
   4'hB :  //
       op_out_int = op_a ^ op_b ;
   default : op_out_int = 'b0;
 endcase
end


endmodule

tb/alu_tb.v
`timescale 1ns/1ps

module testbench_alu;

reg [7:0] op_a;
reg [7:0] op_b;
reg [3:0] inst;

wire [7:0] op_out;

alu8bit i1 (
    .inst(inst),
    .op_a(op_a),
    .op_b(op_b),
    .op_out(op_out)
);

initial begin

    $dumpfile("alu.vcd");
    $dumpvars(0, testbench_alu);

    // =========================
    // ADD
    // =========================
    op_a = 8'd10;
    op_b = 8'd5;
    inst = 4'h1;

    #20;
    $display("ADD: %d + %d = %d", op_a, op_b, op_out);


    // =========================
    // SUBTRACT
    // =========================
    op_a = 8'd10;
    op_b = 8'd5;
    inst = 4'h2;

    #20;
    $display("SUB: %d - %d = %d", op_a, op_b, op_out);


    // =========================
    // MULTIPLY
    // =========================
    op_a = 8'd10;
    op_b = 8'd5;
    inst = 4'h3;

    #20;
    $display("MUL: %d * %d = %d", op_a, op_b, op_out);


    // =========================
    // DIVISION
    // =========================
    op_a = 8'd50;
    op_b = 8'd5;
    inst = 4'h4;

    #20;
    $display("DIV: %d / %d = %d", op_a, op_b, op_out);


    // =========================
    // SHIFT RIGHT
    // =========================
    op_a = 8'b10101010;
    op_b = 8'd0;
    inst = 4'h5;

    #20;
    $display("SHR: %b -> %b", op_a, op_out);


    // =========================
    // SHIFT LEFT
    // =========================
    op_a = 8'b00001111;
    op_b = 8'd0;
    inst = 4'h6;

    #20;
    $display("SHL: %b -> %b", op_a, op_out);


    // =========================
    // BITWISE AND
    // =========================
    op_a = 8'b11001100;
    op_b = 8'b00110011;
    inst = 4'h9;

    #20;
    $display("AND: %b & %b = %b", op_a, op_b, op_out);


    // =========================
    // BITWISE OR
    // =========================
    op_a = 8'b11001100;
    op_b = 8'b00110011;
    inst = 4'hA;

    #20;
    $display("OR : %b | %b = %b", op_a, op_b, op_out);


    // =========================
    // XOR
    // =========================
    op_a = 8'b11001100;
    op_b = 8'b00110011;
    inst = 4'hB;

    #20;
    $display("XOR: %b ^ %b = %b", op_a, op_b, op_out);


    $finish;

end

endmodule

alu.vcd
$date
	Tue Aug 18 15:13:23 2026
$end
$version
	Icarus Verilog
$end
$timescale
	1ps
$end
$scope module testbench_alu $end
$var wire 8 ! op_out [7:0] $end
$var reg 4 " inst [3:0] $end
$var reg 8 # op_a [7:0] $end
$var reg 8 $ op_b [7:0] $end
$scope module i1 $end
$var wire 4 % inst [3:0] $end
$var wire 8 & op_a [7:0] $end
$var wire 8 ' op_b [7:0] $end
$var wire 8 ( op_out [7:0] $end
$var reg 9 ) op_out_int [8:0] $end
$upscope $end
$upscope $end
$enddefinitions $end
#0
$dumpvars
b1111 )
b1111 (
b101 '
b1010 &
b1 %
b101 $
b1010 #
b1 "
b1111 !
$end
#20000
b101 !
b101 (
b101 )
b10 "
b10 %
#40000
b110010 !
b110010 (
b110010 )
b11 "
b11 %
#60000
b1010 !
b1010 (
b1010 )
b100 "
b100 %
b110010 #
b110010 &
#80000
b1010101 !
b1010101 (
b1010101 )
b101 "
b101 %
b0 $
b0 '
b10101010 #
b10101010 &
#100000
b11110 !
b11110 (
b11110 )
b110 "
b110 %
b1111 #
b1111 &
#120000
b0 !
b0 (
b0 )
b1001 "
b1001 %
b110011 $
b110011 '
b11001100 #
b11001100 &
#140000
b11111111 !
b11111111 (
b11111111 )
b1010 "
b1010 %
#160000
b1011 "
b1011 %
